specificity/__init__.py
specificity/specificity.py
specificity-1.0.dist-info/LICENSE
specificity-1.0.dist-info/METADATA
specificity-1.0.dist-info/WHEEL
specificity-1.0.dist-info/top_level.txt
specificity-1.0.dist-info/RECORD
