Metadata-Version: 2.1
Name: specificity
Version: 1.0
Home-page: https://github.com/Dyy0426/specificity.git
License-File: LICENSE
Requires-Dist: pandas
